fandom/FandomPage.py
fandom/__init__.py
fandom/error.py
fandom/fandom.py
fandom/util.py
fandom_py-0.2.1.dist-info/LICENSE
fandom_py-0.2.1.dist-info/METADATA
fandom_py-0.2.1.dist-info/WHEEL
fandom_py-0.2.1.dist-info/top_level.txt
fandom_py-0.2.1.dist-info/RECORD
