Metadata-Version: 2.1
Name: fandom-py
Version: 0.2.1
Summary: Fandom API wrapper for Python
Home-page: https://github.com/NikolajDanger/fandom-py
Author: Nikolaj Gade
Author-email: nikolajgade@live.dk
License: MIT
Keywords: python wikia fandom API
Platform: UNKNOWN
Classifier: License :: OSI Approved :: MIT License
Classifier: Programming Language :: Python :: 3
Requires-Dist: beautifulsoup4
Requires-Dist: requests (<3.0.0,>=2.3.0)
